[
    {
        "_id" : 1,
        "name" : "শাহেদুর রাহমান",
        "img": "https://i.ibb.co/PrTDYbB/Screenshot-2023-11-20-110218.png",
        "education": "বি.এ.এফ শাহীন, কুর্মিটোলা",
        "comment": "জনগনই রেডি না। অবশ্য ভোটের রেশিও দেখলে এইটা বলা যায় না। ফেয়ার ইলেকশন হইলে ভোটের পার্থক্য খুব কমই হয়, আসনে ফারাক হইলেও। রেজিম তো চাইবেই আজীবন থাকতে। কিন্তু জনগনের সম্মতি, চাওয়া অনুসারে থাকার মত যোগ্যতায় থাকলে ঠিক হতো। জোরজবরদস্তি করে ক্ষমতা রাখাটা যেমন হেলদি না, জনগনেরও ওই সক্ষমতা নাই যে সেই পরিমান চ্যালেঞ্জ জানাবে। এখন জনগনকে ততটুকু ক্ষমতা দেওয়ার মত রেজিমের অপেক্ষা করা ছাড়া উপায় নাই। হবে কোন একসময়। সরকারকে প্রশ্নের মুখে রাইখা নিজেদের চাওয়া পাওয়ার বাস্তবায়ন সরকারের মাধ্যমে করা, সরকার সেই জায়গাটা দিতে না পারলে তার পরিবর্তন, এই সংস্কৃতি তৈরি হতে হবে।"
    },
    {
        "_id" : 2,
        "name" : "কানিজ ফাতেমা",
        "img": "https://i.ibb.co/ySn0tzf/Screenshot-2023-11-20-111646.png",
        "education": "উত্তরা হাই স্কুল এন্ড কলেজ",
        "comment": "জনগনই রেডি না। অবশ্য ভোটের রেশিও দেখলে এইটা বলা যায় না। ফেয়ার ইলেকশন হইলে ভোটের পার্থক্য খুব কমই হয়, আসনে ফারাক হইলেও। রেজিম তো চাইবেই আজীবন থাকতে। কিন্তু জনগনের সম্মতি, চাওয়া অনুসারে থাকার মত যোগ্যতায় থাকলে ঠিক হতো। জোরজবরদস্তি করে ক্ষমতা রাখাটা যেমন হেলদি না, জনগনেরও ওই সক্ষমতা নাই যে সেই পরিমান চ্যালেঞ্জ জানাবে। এখন জনগনকে ততটুকু ক্ষমতা দেওয়ার মত রেজিমের অপেক্ষা করা ছাড়া উপায় নাই। হবে কোন একসময়। সরকারকে প্রশ্নের মুখে রাইখা নিজেদের চাওয়া পাওয়ার বাস্তবায়ন সরকারের মাধ্যমে করা, সরকার সেই জায়গাটা দিতে না পারলে তার পরিবর্তন, এই সংস্কৃতি তৈরি হতে হবে।"
    },
    {
        "_id" : 3,
        "name" : "মাকসুদুল আলম",
        "img": "https://i.ibb.co/vv5FDzS/Screenshot-2023-11-20-111452.png",
        "education": "উত্তরা হাই স্কুল এন্ড কলেজ",
        "comment": "জনগনই রেডি না। অবশ্য ভোটের রেশিও দেখলে এইটা বলা যায় না। ফেয়ার ইলেকশন হইলে ভোটের পার্থক্য খুব কমই হয়, আসনে ফারাক হইলেও। রেজিম তো চাইবেই আজীবন থাকতে। কিন্তু জনগনের সম্মতি, চাওয়া অনুসারে থাকার মত যোগ্যতায় থাকলে ঠিক হতো। জোরজবরদস্তি করে ক্ষমতা রাখাটা যেমন হেলদি না, জনগনেরও ওই সক্ষমতা নাই যে সেই পরিমান চ্যালেঞ্জ জানাবে। এখন জনগনকে ততটুকু ক্ষমতা দেওয়ার মত রেজিমের অপেক্ষা করা ছাড়া উপায় নাই। হবে কোন একসময়। সরকারকে প্রশ্নের মুখে রাইখা নিজেদের চাওয়া পাওয়ার বাস্তবায়ন সরকারের মাধ্যমে করা, সরকার সেই জায়গাটা দিতে না পারলে তার পরিবর্তন, এই সংস্কৃতি তৈরি হতে হবে।"
    }
]